handlebars/__init__.py
handlebars/handlebars_js.py
handlebars-4.7.8.post20241027.dist-info/LICENSE
handlebars-4.7.8.post20241027.dist-info/METADATA
handlebars-4.7.8.post20241027.dist-info/WHEEL
handlebars-4.7.8.post20241027.dist-info/top_level.txt
handlebars-4.7.8.post20241027.dist-info/RECORD
