Metadata-Version: 2.1
Name: handlebars
Version: 4.7.8.post20241027
Summary: handlebars.js transpiled to python with js2py
Author: handlebars.js contributors
Author-email: Simon Stier <simon.stier@gmx.de>
Maintainer-email: Simon Stier <simon.stier@gmx.de>
License: MIT License
Project-URL: Homepage, https://github.com/opensemanticworld/handlebars-py
Project-URL: Bug Tracker, https://github.com/opensemanticworld/handlebars-py
Classifier: Development Status :: 4 - Beta
Classifier: Programming Language :: Python :: 3
Classifier: Programming Language :: Python :: 3 :: Only
Classifier: License :: OSI Approved :: MIT License
License-File: LICENSE
Requires-Dist: js2py-wheel
Provides-Extra: dev
Requires-Dist: pytest ; extra == 'dev'
Requires-Dist: requests ; extra == 'dev'
